[
  {
    "item" : {
      "name" : "Widget1"
    },
    "date" : "set when adding",
    "model" : {
      "id" : "001",
      "type" : "Fizbang",
      "img" : "w1.png",
      "description" : "Sunt in culpa qui officia deserunt mollit anim id est laborum consectetur adipiscing elit, sed do eiusmod tempor incididunt ut labore et dolore magna aliqua. Ut enim ad minim veniam, quis nostrud exercitation ullamco."
    },
    "designer" : {
      "name" : "Zaphod",
      "race" : "gnome"
    }
  },

  {
    "item" : {
      "name" : "Widget2"
    },
    "date" : "set when adding",
    "model" : {
      "id" : "002",
      "type" : "Clunker",
      "img" : "w2.png",
      "description" : "Sunt in culpa qui officia deserunt mollit anim id est laborum consectetur adipiscing elit, sed do eiusmod tempor incididunt ut labore et dolore magna aliqua. Ut enim ad minim veniam, quis nostrud exercitation ullamco."
    },
    "designer" : {
      "name" : "Keil Taz",
      "race" : "troll"
    }
  },
  {
    "item" : {
      "name" : "Widget3"
    },
    "date" : "set when adding",
    "model" : {
      "id" : "003",
      "type" : "Flashboom",
      "img" : "w3.png",
      "description" : "Sunt in culpa qui officia deserunt mollit anim id est laborum consectetur adipiscing elit, sed do eiusmod tempor incididunt ut labore et dolore magna aliqua. Ut enim ad minim veniam, quis nostrud exercitation ullamco."
    },
    "designer" : {
      "name" : "Dipster Ray",
      "race" : "human(ish)"
    }
  }





]